Workbook

Sheet Start Here
A1: Freelancer Money Tracker
A3: What this does:
A4: Log invoices and expenses. The Summary sheet shows income, expenses, profit and a suggested tax set-aside for every month, and the Invoices sheet flags who is overdue.
A6: Set up (2 minutes):
A7: 1. Open the Settings sheet and set your tax set-aside rate and default payment terms.
A8: 2. Add one row per invoice on the Invoices sheet. Fill in the blue cells only. Due date, status and days overdue fill themselves in.
A9: 3. When a client pays, enter the Date paid. The invoice turns green and the income lands in that month on the Summary sheet.
A10: 4. Add expenses on the Expenses sheet and pick a category from the drop-down.
A12: Good to know:
A13: - Income is counted when it is paid (cash basis), not when you send the invoice.
A14: - The tax set-aside is a planning estimate (profit x your rate), not tax advice. Ask an accountant what applies to you.
A15: - To look at a past year, type that year into the Settings sheet instead of the formula.
... A22: Grey cells are formulas. Leave them alone.

Sheet Summary
A1: Summary
A2: Cash basis: income counts in the month it was paid.
A3: Year | B3: =Settings!B3
A5: Month | B5: Income | C5: Expenses | D5: Profit | E5: Suggested set-aside | G5: Money owed to you | H5: Amount
A6: =DATE($B$3,1,1) | B6: =SUMIFS(Invoices!$F$2:$F$501,Invoices!$G$2:$G$501,">="&A6,Invoices!$G$2:$G$501,"<"&EDATE(A6,1)) | C6: =SUMIFS(Expenses!$D$2:$D$501,Expenses!$A$2:$A$501,">="&A6,Expenses!$A$2:$A$501,"<"&EDATE(A6,1)) | D6: =B6-C6 | E6: =MAX(0,D6)*Settings!$B$4 | G6: Sent, not yet due | H6: =SUMIFS(Invoices!$F$2:$F$501,Invoices!$H$2:$H$501,"Sent")
A7: =DATE($B$3,2,1) | B7: =SUMIFS(Invoices!$F$2:$F$501,Invoices!$G$2:$G$501,">="&A7,Invoices!$G$2:$G$501,"<"&EDATE(A7,1)) | C7: =SUMIFS(Expenses!$D$2:$D$501,Expenses!$A$2:$A$501,">="&A7,Expenses!$A$2:$A$501,"<"&EDATE(A7,1)) | D7: =B7-C7 | E7: =MAX(0,D7)*Settings!$B$4 | G7: Overdue | H7: =SUMIFS(Invoices!$F$2:$F$501,Invoices!$H$2:$H$501,"Overdue")
A8: =DATE($B$3,3,1) | B8: =SUMIFS(Invoices!$F$2:$F$501,Invoices!$G$2:$G$501,">="&A8,Invoices!$G$2:$G$501,"<"&EDATE(A8,1)) | C8: =SUMIFS(Expenses!$D$2:$D$501,Expenses!$A$2:$A$501,">="&A8,Expenses!$A$2:$A$501,"<"&EDATE(A8,1)) | D8: =B8-C8 | E8: =MAX(0,D8)*Settings!$B$4 | G8: Total outstanding | H8: =H6+H7
A9: =DATE($B$3,4,1) | B9: =SUMIFS(Invoices!$F$2:$F$501,Invoices!$G$2:$G$501,">="&A9,Invoices!$G$2:$G$501,"<"&EDATE(A9,1)) | C9: =SUMIFS(Expenses!$D$2:$D$501,Expenses!$A$2:$A$501,">="&A9,Expenses!$A$2:$A$501,"<"&EDATE(A9,1)) | D9: =B9-C9 | E9: =MAX(0,D9)*Settings!$B$4 | G9: Overdue invoices (count) | H9: =COUNTIF(Invoices!$H$2:$H$501,"Overdue")
A10: =DATE($B$3,5,1) | B10: =SUMIFS(Invoices!$F$2:$F$501,Invoices!$G$2:$G$501,">="&A10,Invoices!$G$2:$G$501,"<"&EDATE(A10,1)) | C10: =SUMIFS(Expenses!$D$2:$D$501,Expenses!$A$2:$A$501,">="&A10,Expenses!$A$2:$A$501,"<"&EDATE(A10,1)) | D10: =B10-C10 | E10: =MAX(0,D10)*Settings!$B$4
A11: =DATE($B$3,6,1) | B11: =SUMIFS(Invoices!$F$2:$F$501,Invoices!$G$2:$G$501,">="&A11,Invoices!$G$2:$G$501,"<"&EDATE(A11,1)) | C11: =SUMIFS(Expenses!$D$2:$D$501,Expenses!$A$2:$A$501,">="&A11,Expenses!$A$2:$A$501,"<"&EDATE(A11,1)) | D11: =B11-C11 | E11: =MAX(0,D11)*Settings!$B$4
A12: =DATE($B$3,7,1) | B12: =SUMIFS(Invoices!$F$2:$F$501,Invoices!$G$2:$G$501,">="&A12,Invoices!$G$2:$G$501,"<"&EDATE(A12,1)) | C12: =SUMIFS(Expenses!$D$2:$D$501,Expenses!$A$2:$A$501,">="&A12,Expenses!$A$2:$A$501,"<"&EDATE(A12,1)) | D12: =B12-C12 | E12: =MAX(0,D12)*Settings!$B$4
A13: =DATE($B$3,8,1) | B13: =SUMIFS(Invoices!$F$2:$F$501,Invoices!$G$2:$G$501,">="&A13,Invoices!$G$2:$G$501,"<"&EDATE(A13,1)) | C13: =SUMIFS(Expenses!$D$2:$D$501,Expenses!$A$2:$A$501,">="&A13,Expenses!$A$2:$A$501,"<"&EDATE(A13,1)) | D13: =B13-C13 | E13: =MAX(0,D13)*Settings!$B$4
A14: =DATE($B$3,9,1) | B14: =SUMIFS(Invoices!$F$2:$F$501,Invoices!$G$2:$G$501,">="&A14,Invoices!$G$2:$G$501,"<"&EDATE(A14,1)) | C14: =SUMIFS(Expenses!$D$2:$D$501,Expenses!$A$2:$A$501,">="&A14,Expenses!$A$2:$A$501,"<"&EDATE(A14,1)) | D14: =B14-C14 | E14: =MAX(0,D14)*Settings!$B$4
A15: =DATE($B$3,10,1) | B15: =SUMIFS(Invoices!$F$2:$F$501,Invoices!$G$2:$G$501,">="&A15,Invoices!$G$2:$G$501,"<"&EDATE(A15,1)) | C15: =SUMIFS(Expenses!$D$2:$D$501,Expenses!$A$2:$A$501,">="&A15,Expenses!$A$2:$A$501,"<"&EDATE(A15,1)) | D15: =B15-C15 | E15: =MAX(0,D15)*Settings!$B$4
A16: =DATE($B$3,11,1) | B16: =SUMIFS(Invoices!$F$2:$F$501,Invoices!$G$2:$G$501,">="&A16,Invoices!$G$2:$G$501,"<"&EDATE(A16,1)) | C16: =SUMIFS(Expenses!$D$2:$D$501,Expenses!$A$2:$A$501,">="&A16,Expenses!$A$2:$A$501,"<"&EDATE(A16,1)) | D16: =B16-C16 | E16: =MAX(0,D16)*Settings!$B$4
A17: =DATE($B$3,12,1) | B17: =SUMIFS(Invoices!$F$2:$F$501,Invoices!$G$2:$G$501,">="&A17,Invoices!$G$2:$G$501,"<"&EDATE(A17,1)) | C17: =SUMIFS(Expenses!$D$2:$D$501,Expenses!$A$2:$A$501,">="&A17,Expenses!$A$2:$A$501,"<"&EDATE(A17,1)) | D17: =B17-C17 | E17: =MAX(0,D17)*Settings!$B$4
A18: Year total | B18: =SUM(B6:B17) | C18: =SUM(C6:C17) | D18: =B18-C18 | E18: =MAX(0,D18)*Settings!$B$4
A19: The year-total set-aside is worked out on full-year profit, so it can differ from the sum of the months.
A22: Expenses by category (year) | B22: Amount
A23: =Settings!D3 | B23: =SUMIFS(Expenses!$D$2:$D$501,Expenses!$C$2:$C$501,A23,Expenses!$A$2:$A$501,">="&DATE($B$3,1,1),Expenses!$A$2:$A$501,"<"&DATE($B$3+1,1,1))
A24: =Settings!D4 | B24: =SUMIFS(Expenses!$D$2:$D$501,Expenses!$C$2:$C$501,A24,Expenses!$A$2:$A$501,">="&DATE($B$3,1,1),Expenses!$A$2:$A$501,"<"&DATE($B$3+1,1,1))
A25: =Settings!D5 | B25: =SUMIFS(Expenses!$D$2:$D$501,Expenses!$C$2:$C$501,A25,Expenses!$A$2:$A$501,">="&DATE($B$3,1,1),Expenses!$A$2:$A$501,"<"&DATE($B$3+1,1,1))
A26: =Settings!D6 | B26: =SUMIFS(Expenses!$D$2:$D$501,Expenses!$C$2:$C$501,A26,Expenses!$A$2:$A$501,">="&DATE($B$3,1,1),Expenses!$A$2:$A$501,"<"&DATE($B$3+1,1,1))
A27: =Settings!D7 | B27: =SUMIFS(Expenses!$D$2:$D$501,Expenses!$C$2:$C$501,A27,Expenses!$A$2:$A$501,">="&DATE($B$3,1,1),Expenses!$A$2:$A$501,"<"&DATE($B$3+1,1,1))
A28: =Settings!D8 | B28: =SUMIFS(Expenses!$D$2:$D$501,Expenses!$C$2:$C$501,A28,Expenses!$A$2:$A$501,">="&DATE($B$3,1,1),Expenses!$A$2:$A$501,"<"&DATE($B$3+1,1,1))
A29: =Settings!D9 | B29: =SUMIFS(Expenses!$D$2:$D$501,Expenses!$C$2:$C$501,A29,Expenses!$A$2:$A$501,">="&DATE($B$3,1,1),Expenses!$A$2:$A$501,"<"&DATE($B$3+1,1,1))
A30: =Settings!D10 | B30: =SUMIFS(Expenses!$D$2:$D$501,Expenses!$C$2:$C$501,A30,Expenses!$A$2:$A$501,">="&DATE($B$3,1,1),Expenses!$A$2:$A$501,"<"&DATE($B$3+1,1,1))
A31: =Settings!D11 | B31: =SUMIFS(Expenses!$D$2:$D$501,Expenses!$C$2:$C$501,A31,Expenses!$A$2:$A$501,">="&DATE($B$3,1,1),Expenses!$A$2:$A$501,"<"&DATE($B$3+1,1,1))
A32: =Settings!D12 | B32: =SUMIFS(Expenses!$D$2:$D$501,Expenses!$C$2:$C$501,A32,Expenses!$A$2:$A$501,">="&DATE($B$3,1,1),Expenses!$A$2:$A$501,"<"&DATE($B$3+1,1,1))
A33: =Settings!D13 | B33: =SUMIFS(Expenses!$D$2:$D$501,Expenses!$C$2:$C$501,A33,Expenses!$A$2:$A$501,">="&DATE($B$3,1,1),Expenses!$A$2:$A$501,"<"&DATE($B$3+1,1,1))

Sheet Settings
A1: Settings
D2: Expense categories (rename freely)
A3: Year to report on | B3: =YEAR(TODAY()) | D3: Software & subscriptions
A4: Tax set-aside rate | B4: 0.25 | D4: Equipment
A5: Default payment terms (days) | B5: 30 | D5: Home office
D6: Travel
D7: Marketing
D8: Professional fees
D9: Education
D10: Bank & payment fees
D11: Other
D12: Custom 1
D13: Custom 2

Sheet Invoices
A1: Invoice # | B1: Client | C1: Description | D1: Issue date | E1: Due date | F1: Amount | G1: Date paid | H1: Status | I1: Days overdue
A2: INV-001 | B2: Northwind Studio | C2: Brand refresh, part 1 | D2: =TODAY()-75 | E2: =IF(D2="","",D2+Settings!$B$5) | F2: 1800 | G2: =TODAY()-30 | H2: =IF(F2="","",IF(G2<>"","Paid",IF(E2="","Sent",IF(E2<TODAY(),"Overdue","Sent")))) | I2: =IF(H2="Overdue",TODAY()-E2,"")
A3: INV-002 | B3: Alder & Finch | C3: Website copy | D3: =TODAY()-52 | E3: =IF(D3="","",D3+Settings!$B$5) | F3: 950 | G3: =TODAY()-16 | H3: =IF(F3="","",IF(G3<>"","Paid",IF(E3="","Sent",IF(E3<TODAY(),"Overdue","Sent")))) | I3: =IF(H3="Overdue",TODAY()-E3,"")
A4: INV-003 | B4: Kestrel Labs | C4: Monthly retainer | D4: =TODAY()-40 | E4: =IF(D4="","",D4+Settings!$B$5) | F4: 2400 | H4: =IF(F4="","",IF(G4<>"","Paid",IF(E4="","Sent",IF(E4<TODAY(),"Overdue","Sent")))) | I4: =IF(H4="Overdue",TODAY()-E4,"")
A5: INV-004 | B5: Northwind Studio | C5: Brand refresh, part 2 | D5: =TODAY()-12 | E5: =IF(D5="","",D5+Settings!$B$5) | F5: 1800 | H5: =IF(F5="","",IF(G5<>"","Paid",IF(E5="","Sent",IF(E5<TODAY(),"Overdue","Sent")))) | I5: =IF(H5="Overdue",TODAY()-E5,"")
A6: INV-005 | B6: Bright Pantry | C6: Menu design | D6: =TODAY()-5 | E6: =IF(D6="","",D6+Settings!$B$5) | F6: 400 | H6: =IF(F6="","",IF(G6<>"","Paid",IF(E6="","Sent",IF(E6<TODAY(),"Overdue","Sent")))) | I6: =IF(H6="Overdue",TODAY()-E6,"")
E7: =IF(D7="","",D7+Settings!$B$5) | H7: =IF(F7="","",IF(G7<>"","Paid",IF(E7="","Sent",IF(E7<TODAY(),"Overdue","Sent")))) | I7: =IF(H7="Overdue",TODAY()-E7,"")
E8: =IF(D8="","",D8+Settings!$B$5) | H8: =IF(F8="","",IF(G8<>"","Paid",IF(E8="","Sent",IF(E8<TODAY(),"Overdue","Sent")))) | I8: =IF(H8="Overdue",TODAY()-E8,"")
E9: =IF(D9="","",D9+Settings!$B$5) | H9: =IF(F9="","",IF(G9<>"","Paid",IF(E9="","Sent",IF(E9<TODAY(),"Overdue","Sent")))) | I9: =IF(H9="Overdue",TODAY()-E9,"")
E10: =IF(D10="","",D10+Settings!$B$5) | H10: =IF(F10="","",IF(G10<>"","Paid",IF(E10="","Sent",IF(E10<TODAY(),"Overdue","Sent")))) | I10: =IF(H10="Overdue",TODAY()-E10,"")
E11: =IF(D11="","",D11+Settings!$B$5) | H11: =IF(F11="","",IF(G11<>"","Paid",IF(E11="","Sent",IF(E11<TODAY(),"Overdue","Sent")))) | I11: =IF(H11="Overdue",TODAY()-E11,"")
E12: =IF(D12="","",D12+Settings!$B$5) | H12: =IF(F12="","",IF(G12<>"","Paid",IF(E12="","Sent",IF(E12<TODAY(),"Overdue","Sent")))) | I12: =IF(H12="Overdue",TODAY()-E12,"")
E13: =IF(D13="","",D13+Settings!$B$5) | H13: =IF(F13="","",IF(G13<>"","Paid",IF(E13="","Sent",IF(E13<TODAY(),"Overdue","Sent")))) | I13: =IF(H13="Overdue",TODAY()-E13,"")
E14: =IF(D14="","",D14+Settings!$B$5) | H14: =IF(F14="","",IF(G14<>"","Paid",IF(E14="","Sent",IF(E14<TODAY(),"Overdue","Sent")))) | I14: =IF(H14="Overdue",TODAY()-E14,"")
E15: =IF(D15="","",D15+Settings!$B$5) | H15: =IF(F15="","",IF(G15<>"","Paid",IF(E15="","Sent",IF(E15<TODAY(),"Overdue","Sent")))) | I15: =IF(H15="Overdue",TODAY()-E15,"")
E16: =IF(D16="","",D16+Settings!$B$5) | H16: =IF(F16="","",IF(G16<>"","Paid",IF(E16="","Sent",IF(E16<TODAY(),"Overdue","Sent")))) | I16: =IF(H16="Overdue",TODAY()-E16,"")
E17: =IF(D17="","",D17+Settings!$B$5) | H17: =IF(F17="","",IF(G17<>"","Paid",IF(E17="","Sent",IF(E17<TODAY(),"Overdue","Sent")))) | I17: =IF(H17="Overdue",TODAY()-E17,"")
E18: =IF(D18="","",D18+Settings!$B$5) | H18: =IF(F18="","",IF(G18<>"","Paid",IF(E18="","Sent",IF(E18<TODAY(),"Overdue","Sent")))) | I18: =IF(H18="Overdue",TODAY()-E18,"")
... E501: =IF(D501="","",D501+Settings!$B$5) | H501: =IF(F501="","",IF(G501<>"","Paid",IF(E501="","Sent",IF(E501<TODAY(),"Overdue","Sent")))) | I501: =IF(H501="Overdue",TODAY()-E501,"")

Sheet Expenses
A1: Date | B1: Vendor | C1: Category | D1: Amount | E1: Notes
A2: =TODAY()-60 | B2: Adobe | C2: Software & subscriptions | D2: 59.99 | E2: Creative suite
A3: =TODAY()-41 | B3: Laptop Co | C3: Equipment | D3: 1299 | E3: New laptop
A4: =TODAY()-22 | B4: Co-working Space | C4: Home office | D4: 180 | E4: Day passes
A5: =TODAY()-9 | B5: Stripe | C5: Bank & payment fees | D5: 31.4 | E5: Processing fees
